ukitai/__init__.py
ukitai/apis/Audio.py
ukitai/apis/Battery.py
ukitai/apis/ColorSensor.py
ukitai/apis/CommonApi.py
ukitai/apis/HumiditySensor.py
ukitai/apis/InfraredSensor.py
ukitai/apis/LedBox.py
ukitai/apis/LedEyes.py
ukitai/apis/LuxSensor.py
ukitai/apis/Motor.py
ukitai/apis/Private.py
ukitai/apis/Screen.py
ukitai/apis/Servo.py
ukitai/apis/SoundSensor.py
ukitai/apis/TouchSensor.py
ukitai/apis/Ultrasonic.py
ukitai/apis/Vision.py
ukitai/apis/__init__.py
ukitai/common/Color.py
ukitai/common/Common.py
ukitai/common/CompType.py
ukitai/common/DataType.py
ukitai/common/RangMode.py
ukitai/common/__init__.py
ukitai/depend/__init__.py
ukitai/depend/binaries.py
ukitai/depend/filecontents.py
ukitai/link/LinkInterface.py
ukitai/link/__init__.py
ukitai/link/uKitAiBleLink.py
ukitai/link/uKitAiLink.py
ukitai/link/uKitAiSerialLink.py
ukitai/link/uKitAiUdpLink.py
ukitai/protos/__init__.py
ukitai/protos/d11_Luxmeter_pb2.py
ukitai/protos/d1A_LedBelt_pb2.py
ukitai/protos/d1B_Lcd_pb2.py
ukitai/protos/d20_VisionModule_pb2.py
ukitai/protos/d2_IntelligentDev_pb2.py
ukitai/protos/d3_Servo_pb2.py
ukitai/protos/d4_Motor_pb2.py
ukitai/protos/d5_Infrared_pb2.py
ukitai/protos/d6_TempHum_pb2.py
ukitai/protos/d7_Sound_pb2.py
ukitai/protos/d8_Led_pb2.py
ukitai/protos/d9_Ultrasonic_pb2.py
ukitai/protos/dB_TouchSwitch_pb2.py
ukitai/protos/dD_Color_pb2.py
ukitai/protos/dE_VoiceRecognition_pb2.py
ukitai/protos/dF_Battery_pb2.py
ukitai/protos/header_pb2.py
ukitai-0.1.5.dist-info/METADATA
ukitai-0.1.5.dist-info/WHEEL
ukitai-0.1.5.dist-info/top_level.txt
ukitai-0.1.5.dist-info/RECORD
