Metadata-Version: 2.1
Name: ukitai
Version: 0.1.5
Summary: Python SDK for uKit AI
Home-page: UNKNOWN
Author: naOKi Chan
Author-email: eduswengineers@ubtrobot.com
License: UNKNOWN
Platform: UNKNOWN
Requires-Dist: protobuf
Requires-Dist: pyserial
Requires-Dist: websocket-client
